ngiab_cal/__main__.py
ngiab_cal/arguments.py
ngiab_cal/custom_logging.py
ngiab_cal/file_paths.py
ngiab_cal/ngiab_cal_template.yaml
ngiab_cal-0.3.3.dist-info/METADATA
ngiab_cal-0.3.3.dist-info/WHEEL
ngiab_cal-0.3.3.dist-info/entry_points.txt
ngiab_cal-0.3.3.dist-info/top_level.txt
ngiab_cal-0.3.3.dist-info/RECORD
