Metadata-Version: 2.4
Name: ngiab-cal
Version: 0.3.3
Summary: A Python CLI tool to simplify hydrologic model calibration for NextGen In A Box (NGIAB) workflows.
Project-URL: Homepage, https://github.com/CIROH-UA/ngiab-cal
Project-URL: Issues, https://github.com/CIROH-UA/ngiab-cal/issues
Keywords: NGIAB,NextGen,hydrologcal modeling,model calibration,ngen-cal,CFE,Noah-OWP,Docker
Requires-Python: >=3.11
Requires-Dist: aiohttp>=3.11.16
Requires-Dist: colorama>=0.4.6
Requires-Dist: hydrotools-nwis-client>=4.1.0
Requires-Dist: pandas>=2.2.3
Requires-Dist: rich>=14.0.0
